CHANGES.rst
MANIFEST.in
README.rst
setup.py
tomcom/__init__.py
tomcom.plone.mediasearch.egg-info/PKG-INFO
tomcom.plone.mediasearch.egg-info/SOURCES.txt
tomcom.plone.mediasearch.egg-info/dependency_links.txt
tomcom.plone.mediasearch.egg-info/entry_points.txt
tomcom.plone.mediasearch.egg-info/namespace_packages.txt
tomcom.plone.mediasearch.egg-info/not-zip-safe
tomcom.plone.mediasearch.egg-info/requires.txt
tomcom.plone.mediasearch.egg-info/top_level.txt
tomcom/plone/__init__.py
tomcom/plone/mediasearch/__init__.py
tomcom/plone/mediasearch/configure.zcml
tomcom/plone/mediasearch/profiles.zcml
tomcom/plone/mediasearch/browser/__init__.py
tomcom/plone/mediasearch/browser/configure.zcml
tomcom/plone/mediasearch/browser/mediasearch/__init__.py
tomcom/plone/mediasearch/browser/mediasearch/browser.py
tomcom/plone/mediasearch/browser/mediasearch/configure.zcml
tomcom/plone/mediasearch/browser/mediasearch/resource/mediasearch_view.css
tomcom/plone/mediasearch/browser/mediasearch/resource/mediasearch_view.js
tomcom/plone/mediasearch/browser/mediasearch/templates/js_mediasearch_base.pt
tomcom/plone/mediasearch/browser/mediasearch/templates/js_mediasearch_detail_base.pt
tomcom/plone/mediasearch/browser/mediasearch/templates/js_mediasearch_detail_file.pt
tomcom/plone/mediasearch/browser/mediasearch/templates/js_mediasearch_detail_image.pt
tomcom/plone/mediasearch/browser/mediasearch/templates/js_mediasearch_file.pt
tomcom/plone/mediasearch/browser/mediasearch/templates/js_mediasearch_image.pt
tomcom/plone/mediasearch/browser/mediasearch/templates/js_mediasearch_listing.pt
tomcom/plone/mediasearch/browser/mediasearch/templates/js_mediasearch_paste.pt
tomcom/plone/mediasearch/browser/mediasearch/templates/mediasearch_view.pt
tomcom/plone/mediasearch/locales/mediasearch.pot
tomcom/plone/mediasearch/locales/de/LC_MESSAGES/mediasearch.po
tomcom/plone/mediasearch/profiles/default/actions.xml
tomcom/plone/mediasearch/profiles/default/catalog.xml