Metadata-Version: 1.1
Name: tomcom.plone.mediasearch
Version: 4.3.0.2
Summary: Media search
Home-page: http://stash.tomcom.de/scm/PLONE/tomcom.plone.mediasearch.git
Author: tomcom GmbH
Author-email: mailto:info@tomcom.de
License: GPL2
Keywords: tomcom plone
Platform: UNKNOWN
Classifier: Framework :: Plone
Classifier: Programming Language :: Python
Classifier: Topic :: Software Development :: Libraries :: Python Modules
